MANIFEST.in
README.md
flask_hmacauth.py
setup.py
flask_hmacauth.egg-info/PKG-INFO
flask_hmacauth.egg-info/SOURCES.txt
flask_hmacauth.egg-info/dependency_links.txt
flask_hmacauth.egg-info/not-zip-safe
flask_hmacauth.egg-info/top_level.txt