Metadata-Version: 1.1
Name: flask-hmacauth
Version: 0.3.9
Summary: A module to simplify working with HMAC auth in Flask apps
Home-page: http://www.github.com/Phillipmartin/flask-hmacauth
Author: Philip Martin
Author-email: phillip.martin@gmail.com
License: MIT
Platform: UNKNOWN
Classifier: Development Status :: 4 - Beta
Classifier: Intended Audience :: Developers
Classifier: Intended Audience :: System Administrators
Classifier: License :: OSI Approved :: MIT License
Classifier: Programming Language :: Python
Classifier: Topic :: Security
Classifier: Topic :: Software Development :: Libraries :: Python Modules
Requires: flask
